hm_matrix_bridge/__init__.py
hm_matrix_bridge/__main__.py
hm_matrix_bridge/matrixapi.py
hm_matrix_bridge/version.py
HiveMind_matrix_bridge-0.1.1.dist-info/LICENSE
HiveMind_matrix_bridge-0.1.1.dist-info/METADATA
HiveMind_matrix_bridge-0.1.1.dist-info/WHEEL
HiveMind_matrix_bridge-0.1.1.dist-info/entry_points.txt
HiveMind_matrix_bridge-0.1.1.dist-info/top_level.txt
HiveMind_matrix_bridge-0.1.1.dist-info/RECORD
