Metadata-Version: 2.1
Name: HiveMind-matrix-bridge
Version: 0.1.1
Summary: matrix bridge for hivemind
Home-page: https://github.com/JarbasHiveMind/HiveMind-matrix-bridge
Author: jarbasAI
Author-email: jarbasai@mailfence.com
License: MIT
License-File: LICENSE
Requires-Dist: hivemind-bus-client<1.0.0,>=0.4.2
Requires-Dist: click
Requires-Dist: python-matrixbot>=0.4.0
Requires-Dist: ovos-solver-hivemind-plugin
